pgwarehouse/__init__.py
pgwarehouse/__main__.py
pgwarehouse/backend.py
pgwarehouse/clickhouse_backend.py
pgwarehouse/duckdb_backend.py
pgwarehouse/pgwarehouse.py
pgwarehouse/snowflake_backend.py
pgwarehouse/tests/__init__.py
pgwarehouse/tests/data/local_parks.csv
pgwarehouse/tests/data/my_orders.csv
pgwarehouse/tests/data/users10.csv
pgwarehouse/tests/pg_setup.sql
pgwarehouse/tests/test_postgres.py
pgwarehouse-0.1.5.dist-info/LICENSE.txt
pgwarehouse-0.1.5.dist-info/METADATA
pgwarehouse-0.1.5.dist-info/WHEEL
pgwarehouse-0.1.5.dist-info/entry_points.txt
pgwarehouse-0.1.5.dist-info/RECORD
