Metadata-Version: 2.1
Name: pgwarehouse
Version: 0.1.5
Summary: Easily sync your Postgres database to your data warehouse.
Author: Scott Persinger
Author-email: scottpersinger@gmail.com
Requires-Python: >=3.9,<4.0
Classifier: Programming Language :: Python :: 3
Classifier: Programming Language :: Python :: 3.9
Classifier: Programming Language :: Python :: 3.10
Classifier: Programming Language :: Python :: 3.11
Classifier: Programming Language :: Python :: 3.12
Requires-Dist: clickhouse-driver (>=0.2.7,<0.3.0)
Requires-Dist: duckdb (>=0.10.2,<0.11.0)
Requires-Dist: psycopg2 (>=2.9.9,<3.0.0)
Requires-Dist: pytest (>=8.2.0,<9.0.0)
Requires-Dist: python-dotenv (>=1.0.1,<2.0.0)
Requires-Dist: pyyaml (>=6.0.1,<7.0.0)
Requires-Dist: snowflake-connector-python (>=3.10.0,<4.0.0)
Requires-Dist: tabulate (>=0.9.0,<0.10.0)
Requires-Dist: testing-postgresql (>=1.3.0,<2.0.0)
